deshi_hello_world/__init__.py
deshi_hello_world/cli.py
deshi_hello_world-0.14.dist-info/METADATA
deshi_hello_world-0.14.dist-info/WHEEL
deshi_hello_world-0.14.dist-info/entry_points.txt
deshi_hello_world-0.14.dist-info/top_level.txt
deshi_hello_world-0.14.dist-info/RECORD
